CHANGELOG.txt
LICENSE.txt
README.txt
buffet.py
ez_setup.py
setup.py
Buffet.egg-info/PKG-INFO
Buffet.egg-info/SOURCES.txt
Buffet.egg-info/dependency_links.txt
Buffet.egg-info/not-zip-safe
Buffet.egg-info/top_level.txt
examples/README.TXT
examples/buffet_demo.py
examples/templates/__init__.py
examples/templates/cheetah/__init__.py
examples/templates/cheetah/test.tmpl
examples/templates/cherrytemplate/test.tpl
examples/templates/kid/__init__.py
examples/templates/kid/test.kid
examples/templates/myghty/test.myt
examples/templates/string/body.tmpl
examples/templates/string/foot.tmpl
examples/templates/string/generic_template.tmpl
examples/templates/string/head.tmpl
examples/templates/xsl/test.xsl
