Metadata-Version: 1.0
Name: Buffet
Version: 1.0
Summary: A flexible templating filter for CherryPy
Home-page: http://projects.dowski.com/view/buffet
Author: Christian Wyglendowski
Author-email: christian@dowski.com
License: MIT
Platform: UNKNOWN
